delivery_api_client/__init__.py
delivery_api_client/api_client.py
delivery_api_client/configuration.py
delivery_api_client/exceptions.py
delivery_api_client/rest.py
delivery_api_client/Model/__init__.py
delivery_api_client/Model/action.py
delivery_api_client/Model/address.py
delivery_api_client/Model/analytics_payload.py
delivery_api_client/Model/analytics_request.py
delivery_api_client/Model/analytics_response.py
delivery_api_client/Model/application.py
delivery_api_client/Model/audience_manager.py
delivery_api_client/Model/authenticated_state.py
delivery_api_client/Model/browser.py
delivery_api_client/Model/channel_type.py
delivery_api_client/Model/context.py
delivery_api_client/Model/customer_id.py
delivery_api_client/Model/decisioning_method.py
delivery_api_client/Model/delivery_request.py
delivery_api_client/Model/delivery_response.py
delivery_api_client/Model/device_type.py
delivery_api_client/Model/execute_request.py
delivery_api_client/Model/execute_response.py
delivery_api_client/Model/experience_cloud.py
delivery_api_client/Model/geo.py
delivery_api_client/Model/logging_type.py
delivery_api_client/Model/mbox_request.py
delivery_api_client/Model/mbox_request_all_of.py
delivery_api_client/Model/mbox_response.py
delivery_api_client/Model/metric.py
delivery_api_client/Model/metric_type.py
delivery_api_client/Model/mobile_platform.py
delivery_api_client/Model/mobile_platform_type.py
delivery_api_client/Model/model_property.py
delivery_api_client/Model/notification.py
delivery_api_client/Model/notification_all_of.py
delivery_api_client/Model/notification_mbox.py
delivery_api_client/Model/notification_page_load.py
delivery_api_client/Model/notification_response.py
delivery_api_client/Model/notification_view.py
delivery_api_client/Model/option.py
delivery_api_client/Model/option_type.py
delivery_api_client/Model/order.py
delivery_api_client/Model/page_load_response.py
delivery_api_client/Model/prefetch_mbox_response.py
target_python_sdk-1.1.0.dist-info/METADATA
target_python_sdk-1.1.0.dist-info/WHEEL
target_python_sdk-1.1.0.dist-info/top_level.txt
target_python_sdk-1.1.0.dist-info/RECORD
