Metadata-Version: 2.1
Name: target-python-sdk
Version: 1.1.0
Summary: Adobe Target Python SDK
Home-page: https://github.com/adobe/target-python-sdk
License: UNKNOWN
Platform: UNKNOWN
Requires-Python: >=2.7,>=3.6
